wikinator/.DS_Store
wikinator/__init__.py
wikinator/converter.py
wikinator/docxit.py
wikinator/gdrive.py
wikinator/page.py
wikinator/wiki.py
wikinator-0.6.2.dist-info/WHEEL
wikinator-0.6.2.dist-info/entry_points.txt
wikinator-0.6.2.dist-info/METADATA
wikinator-0.6.2.dist-info/RECORD
