Metadata-Version: 2.3
Name: wikinator
Version: 0.6.2
Summary: Convert Google docs to markdown
Requires-Dist: dotenv>=0.9.9
Requires-Dist: google-api-python-client>=2.175.0
Requires-Dist: google-auth-httplib2>=0.2.0
Requires-Dist: google-auth-oauthlib>=1.2.2
Requires-Dist: gql[all]>=3.5.3
Requires-Dist: pytest>=8.4.1
Requires-Dist: python-docx>=1.2.0
Requires-Dist: typer-slim>=0.16.0
Requires-Python: >=3.13
Project-URL: Documentation, https://github.com/philion/wikinator#readme
Project-URL: Issues, https://github.com/philion/wikinator/issues
Project-URL: Source, https://github.com/philion/wikinator
